graphix_perceval/__init__.py
graphix_perceval/clifford.py
graphix_perceval/converter.py
graphix_perceval/experiment.py
graphix_perceval/version.py
tests/__init__.py
tests/test_clifford.py
tests/test_converter.py
graphix_perceval-0.0.2.dist-info/LICENSE
graphix_perceval-0.0.2.dist-info/METADATA
graphix_perceval-0.0.2.dist-info/WHEEL
graphix_perceval-0.0.2.dist-info/top_level.txt
graphix_perceval-0.0.2.dist-info/RECORD
